{
  "type": "minecraft:chest",
  "pools": [
    {
      "bonus_rolls": 0.0,
      "conditions": [
        {
          "chance": 0.15,
          "condition": "minecraft:random_chance"
        }
      ],
      "entries": [
        {
          "type": "minecraft:item",
          "functions": [
            {
              "add": false,
              "count": 1.0,
              "function": "minecraft:set_count"
            },
            {
              "add": false,
              "damage": {
                "type": "minecraft:uniform",
                "max": 0.9,
                "min": 0.1
              },
              "function": "minecraft:set_damage"
            }
          ],
          "name": "somemod:arctic_hat"
        }
      ],
      "rolls": 1.0
    },
    {
      "bonus_rolls": 0.0,
      "conditions": [
        {
          "chance": 0.15,
          "condition": "minecraft:random_chance"
        }
      ],
      "entries": [
        {
          "type": "minecraft:item",
          "functions": [
            {
              "add": false,
              "count": 1.0,
              "function": "minecraft:set_count"
            },
            {
              "add": false,
              "damage": {
                "type": "minecraft:uniform",
                "max": 0.9,
                "min": 0.1
              },
              "function": "minecraft:set_damage"
            }
          ],
          "name": "somemod:arctic_jacket"
        }
      ],
      "rolls": 1.0
    },
    {
      "bonus_rolls": 0.0,
      "conditions": [
        {
          "chance": 0.15,
          "condition": "minecraft:random_chance"
        }
      ],
      "entries": [
        {
          "type": "minecraft:item",
          "functions": [
            {
              "add": false,
              "count": 1.0,
              "function": "minecraft:set_count"
            },
            {
              "add": false,
              "damage": {
                "type": "minecraft:uniform",
                "max": 0.9,
                "min": 0.1
              },
              "function": "minecraft:set_damage"
            }
          ],
          "name": "somemod:arctic_pants"
        }
      ],
      "rolls": 1.0
    },
    {
      "bonus_rolls": 0.0,
      "conditions": [
        {
          "chance": 0.15,
          "condition": "minecraft:random_chance"
        }
      ],
      "entries": [
        {
          "type": "minecraft:item",
          "functions": [
            {
              "add": false,
              "count": 1.0,
              "function": "minecraft:set_count"
            },
            {
              "add": false,
              "damage": {
                "type": "minecraft:uniform",
                "max": 0.9,
                "min": 0.1
              },
              "function": "minecraft:set_damage"
            }
          ],
          "name": "somemod:arctic_boots"
        }
      ],
      "rolls": 1.0
    }
  ]
}