{
  "type": "minecraft:chest",
  "pools": [
    {
      "bonus_rolls": 0.0,
      "entries": [
        {
          "type": "minecraft:loot_table",
          "name": "somemod:chests/spruce_chest_arctic_armor"
        },
        {
          "type": "minecraft:loot_table",
          "name": "somemod:chests/spruce_chest_arctic_armor"
        },
        {
          "type": "minecraft:loot_table",
          "name": "somemod:chests/spruce_chest_glacier_armor"
        }
      ],
      "rolls": 1.0
    },
    {
      "bonus_rolls": 0.0,
      "entries": [
        {
          "type": "minecraft:item",
          "name": "minecraft:torch",
          "weight": 8
        },
        {
          "type": "minecraft:item",
          "name": "minecraft:coal",
          "weight": 2
        },
        {
          "type": "minecraft:item",
          "name": "minecraft:stick",
          "weight": 2
        },
        {
          "type": "minecraft:item",
          "name": "minecraft:spruce_log",
          "weight": 2
        },
        {
          "type": "minecraft:item",
          "name": "minecraft:spruce_planks",
          "weight": 2
        },
        {
          "type": "minecraft:item",
          "name": "minecraft:spruce_fence",
          "weight": 2
        },
        {
          "type": "minecraft:item",
          "name": "minecraft:crafting_table"
        },
        {
          "type": "minecraft:item",
          "name": "minecraft:furnace"
        }
      ],
      "rolls": {
        "type": "minecraft:uniform",
        "max": 12.0,
        "min": 8.0
      }
    },
    {
      "bonus_rolls": 0.0,
      "entries": [
        {
          "type": "minecraft:item",
          "functions": [
            {
              "add": false,
              "count": {
                "type": "minecraft:uniform",
                "max": 3.0,
                "min": 0.0
              },
              "function": "minecraft:set_count"
            }
          ],
          "name": "minecraft:bread"
        },
        {
          "type": "minecraft:item",
          "functions": [
            {
              "add": false,
              "count": {
                "type": "minecraft:uniform",
                "max": 6.0,
                "min": 0.0
              },
              "function": "minecraft:set_count"
            }
          ],
          "name": "minecraft:apple"
        }
      ],
      "rolls": 1.0
    },
    {
      "bonus_rolls": 0.0,
      "entries": [
        {
          "type": "minecraft:item",
          "functions": [
            {
              "add": false,
              "count": 1.0,
              "function": "minecraft:set_count"
            },
            {
              "add": false,
              "damage": {
                "type": "minecraft:uniform",
                "max": 0.9,
                "min": 0.1
              },
              "function": "minecraft:set_damage"
            }
          ],
          "name": "minecraft:stone_sword"
        },
        {
          "type": "minecraft:item",
          "functions": [
            {
              "add": false,
              "count": 1.0,
              "function": "minecraft:set_count"
            },
            {
              "add": false,
              "damage": {
                "type": "minecraft:uniform",
                "max": 0.9,
                "min": 0.1
              },
              "function": "minecraft:set_damage"
            }
          ],
          "name": "minecraft:stone_pickaxe"
        },
        {
          "type": "minecraft:item",
          "name": "minecraft:campfire"
        }
      ],
      "rolls": 1.0
    },
    {
      "bonus_rolls": 0.0,
      "conditions": [
        {
          "chance": 0.5,
          "condition": "minecraft:random_chance"
        }
      ],
      "entries": [
        {
          "type": "minecraft:item",
          "functions": [
            {
              "add": false,
              "count": {
                "type": "minecraft:uniform",
                "max": 3.0,
                "min": 1.0
              },
              "function": "minecraft:set_count"
            }
          ],
          "name": "minecraft:iron_ingot"
        },
        {
          "type": "minecraft:item",
          "functions": [
            {
              "add": false,
              "count": {
                "type": "minecraft:uniform",
                "max": 3.0,
                "min": 1.0
              },
              "function": "minecraft:set_count"
            }
          ],
          "name": "minecraft:gold_ingot"
        }
      ],
      "rolls": 1.0
    },
    {
      "bonus_rolls": 0.0,
      "conditions": [
        {
          "chance": 0.1,
          "condition": "minecraft:random_chance"
        }
      ],
      "entries": [
        {
          "type": "minecraft:item",
          "name": "minecraft:emerald"
        }
      ],
      "rolls": 1.0
    }
  ]
}